{
  "element": "dbp-knowledge-base-web-page-element-view-demo-activity",
  "module_src": "dbp-knowledge-base-web-page-element-view-demo-activity.js",
  "routing_name": "knowledge-base-web-page-element-view",
  "name": {
    "de": "Knowledgebase webpage element view",
    "en": "Knowledgebase webpage element view"
  },
  "short_name": {
    "de": "Knowledgebase webpage element view",
    "en": "Knowledgebase webpage element view"
  },
  "description": {
    "de": "Erlaubt das Einfügen von Webinhalten",
    "en": "Allows the inserting of web content"
  },
  "subscribe": "lang:lang,entry-point-url:entry-point-url,auth:auth"
}
